{
  "version": "5.2.1",
  "flags": {},
  "shapes": [
    {
      "label": "couch",
      "points": [
        [
          2148.964599609375,
          2219.238525390625
        ],
        [
          3656.80615234375,
          2880.3095703125
        ]
      ],
      "group_id": 0,
      "shape_type": "rectangle",
      "flags": {
        "instance_id": 0
      }
    },
    {
      "label": "couch",
      "points": [
        [
          4866.08544921875,
          2100.470703125
        ],
        [
          5895.8310546875,
          2779.703369140625
        ]
      ],
      "group_id": 1,
      "shape_type": "rectangle",
      "flags": {
        "instance_id": 1
      }
    },
    {
      "label": "chair",
      "points": [
        [
          7467.1318359375,
          2481.084716796875
        ],
        [
          7765.4306640625,
          3280.181884765625
        ]
      ],
      "group_id": 2,
      "shape_type": "rectangle",
      "flags": {
        "instance_id": 2
      }
    },
    {
      "label": "chair",
      "points": [
        [
          0.0,
          2802.48583984375
        ],
        [
          536.7202758789062,
          3332.795654296875
        ]
      ],
      "group_id": 3,
      "shape_type": "rectangle",
      "flags": {
        "instance_id": 3
      }
    },
    {
      "label": "chair",
      "points": [
        [
          6208.62841796875,
          2400.0
        ],
        [
          7028.28564453125,
          3351.0185546875
        ]
      ],
      "group_id": 4,
      "shape_type": "rectangle",
      "flags": {
        "instance_id": 4
      }
    }
  ],
  "imagePath": "9C4A9300-be2f4c26f1.png",
  "imageData": null,
  "imageHeight": 3884,
  "imageWidth": 7768
}