{
  "version": "5.2.1",
  "flags": {},
  "shapes": [
    {
      "label": "person",
      "points": [
        [
          981.094970703125,
          108.32499694824219
        ],
        [
          1567.905029296875,
          1052.675048828125
        ]
      ],
      "group_id": 0,
      "shape_type": "rectangle",
      "flags": {
        "instance_id": 0
      }
    },
    {
      "label": "cup",
      "points": [
        [
          875.7150268554688,
          420.6700134277344
        ],
        [
          933.2849731445312,
          487.3299865722656
        ]
      ],
      "group_id": 1,
      "shape_type": "rectangle",
      "flags": {
        "instance_id": 1
      }
    },
    {
      "label": "chair",
      "points": [
        [
          376.2449951171875,
          451.135009765625
        ],
        [
          730.7550048828125,
          1029.864990234375
        ]
      ],
      "group_id": 2,
      "shape_type": "rectangle",
      "flags": {
        "instance_id": 2
      }
    },
    {
      "label": "chair",
      "points": [
        [
          1249.0350341796875,
          464.9849853515625
        ],
        [
          1645.9649658203125,
          1074.0150146484375
        ]
      ],
      "group_id": 3,
      "shape_type": "rectangle",
      "flags": {
        "instance_id": 3
      }
    },
    {
      "label": "bottle",
      "points": [
        [
          1460.7950439453125,
          155.42999267578125
        ],
        [
          1502.2049560546875,
          270.57000732421875
        ]
      ],
      "group_id": 4,
      "shape_type": "rectangle",
      "flags": {
        "instance_id": 4
      }
    },
    {
      "label": "person",
      "points": [
        [
          762.0800170898438,
          123.61000061035156
        ],
        [
          1149.9200439453125,
          1010.3900146484375
        ]
      ],
      "group_id": 5,
      "shape_type": "rectangle",
      "flags": {
        "instance_id": 5
      }
    },
    {
      "label": "tie",
      "points": [
        [
          949.844970703125,
          303.43499755859375
        ],
        [
          981.155029296875,
          417.56500244140625
        ]
      ],
      "group_id": 6,
      "shape_type": "rectangle",
      "flags": {
        "instance_id": 6
      }
    },
    {
      "label": "bottle",
      "points": [
        [
          1566.8199462890625,
          152.2550048828125
        ],
        [
          1603.1800537109375,
          302.7449951171875
        ]
      ],
      "group_id": 7,
      "shape_type": "rectangle",
      "flags": {
        "instance_id": 7
      }
    },
    {
      "label": "bottle",
      "points": [
        [
          1517.7850341796875,
          154.27000427246094
        ],
        [
          1561.2149658203125,
          301.7300109863281
        ]
      ],
      "group_id": 8,
      "shape_type": "rectangle",
      "flags": {
        "instance_id": 8
      }
    },
    {
      "label": "bottle",
      "points": [
        [
          1133.800048828125,
          283.55499267578125
        ],
        [
          1174.199951171875,
          373.44500732421875
        ]
      ],
      "group_id": 9,
      "shape_type": "rectangle",
      "flags": {
        "instance_id": 9
      }
    },
    {
      "label": "person",
      "points": [
        [
          431.9800109863281,
          92.44499969482422
        ],
        [
          1042.02001953125,
          1012.5549926757812
        ]
      ],
      "group_id": 10,
      "shape_type": "rectangle",
      "flags": {
        "instance_id": 10
      }
    },
    {
      "label": "bottle",
      "points": [
        [
          1522.699951171875,
          16.510000228881836
        ],
        [
          1583.300048828125,
          115.48999786376953
        ]
      ],
      "group_id": 11,
      "shape_type": "rectangle",
      "flags": {
        "instance_id": 11
      }
    },
    {
      "label": "bottle",
      "points": [
        [
          373.79998779296875,
          119.2300033569336
        ],
        [
          414.20001220703125,
          274.7699890136719
        ]
      ],
      "group_id": 12,
      "shape_type": "rectangle",
      "flags": {
        "instance_id": 12
      }
    },
    {
      "label": "cup",
      "points": [
        [
          1053.719970703125,
          416.6700134277344
        ],
        [
          1110.280029296875,
          483.3299865722656
        ]
      ],
      "group_id": 13,
      "shape_type": "rectangle",
      "flags": {
        "instance_id": 13
      }
    },
    {
      "label": "bottle",
      "points": [
        [
          1480.81005859375,
          9.470000267028809
        ],
        [
          1519.18994140625,
          116.52999877929688
        ]
      ],
      "group_id": 14,
      "shape_type": "rectangle",
      "flags": {
        "instance_id": 14
      }
    },
    {
      "label": "person",
      "points": [
        [
          1130.1400146484375,
          177.81500244140625
        ],
        [
          1303.8599853515625,
          417.18499755859375
        ]
      ],
      "group_id": 15,
      "shape_type": "rectangle",
      "flags": {
        "instance_id": 15
      }
    },
    {
      "label": "bottle",
      "points": [
        [
          306.80499267578125,
          90.08499908447266
        ],
        [
          346.19500732421875,
          274.9150085449219
        ]
      ],
      "group_id": 16,
      "shape_type": "rectangle",
      "flags": {
        "instance_id": 16
      }
    },
    {
      "label": "bottle",
      "points": [
        [
          339.82000732421875,
          111.19999694824219
        ],
        [
          376.17999267578125,
          272.79998779296875
        ]
      ],
      "group_id": 17,
      "shape_type": "rectangle",
      "flags": {
        "instance_id": 17
      }
    },
    {
      "label": "dining table",
      "points": [
        [
          713.0750122070312,
          446.9849853515625
        ],
        [
          1303.925048828125,
          1056.0150146484375
        ]
      ],
      "group_id": 18,
      "shape_type": "rectangle",
      "flags": {
        "instance_id": 18
      }
    },
    {
      "label": "bottle",
      "points": [
        [
          408.8299865722656,
          88.05000305175781
        ],
        [
          443.1700134277344,
          279.95001220703125
        ]
      ],
      "group_id": 19,
      "shape_type": "rectangle",
      "flags": {
        "instance_id": 19
      }
    },
    {
      "label": "bottle",
      "points": [
        [
          1588.905029296875,
          11.489999771118164
        ],
        [
          1608.094970703125,
          114.51000213623047
        ]
      ],
      "group_id": 20,
      "shape_type": "rectangle",
      "flags": {
        "instance_id": 20
      }
    },
    {
      "label": "bottle",
      "points": [
        [
          1672.43505859375,
          68.80000305175781
        ],
        [
          1786.56494140625,
          109.19999694824219
        ]
      ],
      "group_id": 21,
      "shape_type": "rectangle",
      "flags": {
        "instance_id": 21
      }
    }
  ],
  "imagePath": "hdr_00705.png",
  "imageData": null,
  "imageHeight": 1080,
  "imageWidth": 1920
}