{
  "version": "5.2.1",
  "flags": {},
  "shapes": [
    {
      "label": "person",
      "points": [
        [
          353.2133483886719,
          201.3333282470703
        ],
        [
          512.1199951171875,
          605.3333129882812
        ]
      ],
      "group_id": 0,
      "shape_type": "rectangle",
      "flags": {
        "instance_id": 0
      }
    },
    {
      "label": "person",
      "points": [
        [
          0.0,
          0.0
        ],
        [
          321.5966796875,
          719.0
        ]
      ],
      "group_id": 1,
      "shape_type": "rectangle",
      "flags": {
        "instance_id": 1
      }
    }
  ],
  "imagePath": "hdr_01206.png",
  "imageData": null,
  "imageHeight": 720,
  "imageWidth": 1280
}